MANIFEST.in
README.md
requirements.txt
setup.cfg
setup.py
versioneer.py
botcity/plugins/aws/secretsmanager/__init__.py
botcity/plugins/aws/secretsmanager/_version.py
botcity/plugins/aws/secretsmanager/plugin.py
botcity/plugins/aws/secretsmanager/utils.py
botcity_aws_secretsmanager_plugin.egg-info/PKG-INFO
botcity_aws_secretsmanager_plugin.egg-info/SOURCES.txt
botcity_aws_secretsmanager_plugin.egg-info/dependency_links.txt
botcity_aws_secretsmanager_plugin.egg-info/requires.txt
botcity_aws_secretsmanager_plugin.egg-info/top_level.txt